{"id":"item-ada550ffc7df","sku":"_dHjHj_OV8ZdXFG3KTrH3P9sJD1EQrJhXVUyPcfA","name_en":"🗯💰","name_cn":"🗯💰\n▪️LE 5 À 7▪\nThe Y brand's much-anticipated underarm bag is finally here!!️\nI loved the name at first sight; it is inspired by the niche film 'Cléo from 5 to 7', telling the story of the 5-7 PM gap between work and home, and how the protagonist Cléo gradually reveals her independent side. Looking back at the bag itself, the silhouette is simple and structured, appearing firm yet not too sharp.\nPaired with the brand's signature insert buckle, the overall look gives a unique temperament that is both classic and elegant, yet very modern and stylish.\nSize: 24.5x16x6cm\nModel No.: 657228 Patent Leather","specs":{"source":"wsxcme","sourceId":"_dHjHj_OV8ZdXFG3KTrH3P9sJD1EQrJhXVUyPcfA","sourceTagId":47002761,"sourceTagName":"Saint Laurent/women's bag","modelNumber":"657228","dimensions":{"lengthCm":24.5,"heightCm":16,"widthCm":6},"rawTitle":"🗯💰\n▪️LE 5 À 7▪\nThe Y brand's much-anticipated underarm bag is finally here!!️\nI loved the name at first sight; it is inspired by the niche film 'Cléo from 5 to 7', telling the story of the 5-7 PM gap between work and home, and how the protagonist Cléo gradually reveals her independent side. Looking back at the bag itself, the silhouette is simple and structured, appearing firm yet not too sharp.\nPaired with the brand's signature insert buckle, the overall look gives a unique temperament that is both classic and elegant, yet very modern and stylish.\nSize: 24.5x16x6cm\nModel No.: 657228 Patent Leather"},"price":null,"currency":"CNY","moq":1,"category":"ysl-women-bags","status":"active","alibaba_url":null,"images":["https://xcimg.szwego.com/img/58395cbb/20240108/a1704700832577_5700.jpg","https://xcimg.szwego.com/img/58395cbb/20240108/a1704700832605_0537.jpg","https://xcimg.szwego.com/img/58395cbb/20240108/a1704700832877_3673.jpg","https://xcimg.szwego.com/img/58395cbb/20240108/a1704700832681_3426.jpg","https://xcimg.szwego.com/img/58395cbb/20240108/a1704700832564_2374.jpg","https://xcimg.szwego.com/img/58395cbb/20240108/a1704700832430_1770.jpg","https://xcimg.szwego.com/img/58395cbb/20240108/a1704700836158_4623.jpg","https://xcimg.szwego.com/img/58395cbb/20240108/a1704700836316_2611.jpg","https://xcimg.szwego.com/img/58395cbb/20240108/a1704700836410_6534.jpg"],"created_at":"2025-07-20T03:05:44.228Z"}
