{"id":"item-91db15c9c0f7","sku":"_dgAgA2-FA1XUcJs5PrZEY9-3ZdXa1xwGUhHHKGQ","name_en":",High Version","name_cn":",High Version\nNew Coconut Tree Dark Blue Small Size\nDIOR Book Tote Shopping Bag\nLarger than mini size, slightly smaller than the original small size\nThe vintage D-letter embroidery that swept the fashion world\nFully handcrafted 3D embroidery, textured and raised\nRich vintage artistic atmosphere, simply a walking work of art\nSuper large capacity, it's amazing\nEspecially suitable for girls who want to take their whole home out\nMom bag, briefcase, travel companion\nMust-have for fashionistas to style their look\n26.5×21×14cm","specs":{"source":"wsxcme","sourceId":"_dgAgA2-FA1XUcJs5PrZEY9-3ZdXa1xwGUhHHKGQ","sourceTagId":47002747,"sourceTagName":"Dior/women's bag","rawTitle":",High Version\nNew Coconut Tree Dark Blue Small Size\nDIOR Book Tote Shopping Bag\nLarger than mini size, slightly smaller than the original small size\nThe vintage D-letter embroidery that swept the fashion world\nFully handcrafted 3D embroidery, textured and raised\nRich vintage artistic atmosphere, simply a walking work of art\nSuper large capacity, it's amazing\nEspecially suitable for girls who want to take their whole home out\nMom bag, briefcase, travel companion\nMust-have for fashionistas to style their look\n26.5×21×14cm"},"price":null,"currency":"CNY","moq":1,"category":"dior-women-bags","status":"active","alibaba_url":null,"images":["https://xcimg.szwego.com/img/ec683d96/20250804/i1754256019_9147_2.jpg","https://xcimg.szwego.com/img/ec683d96/20250804/i1754256020_223_4.jpg","https://xcimg.szwego.com/img/ec683d96/20250804/i1754256020_3801_8.jpg","https://xcimg.szwego.com/img/ec683d96/20250804/i1754256020_8109_7.jpg","https://xcimg.szwego.com/img/ec683d96/20250804/i1754256019_8644_1.jpg","https://xcimg.szwego.com/img/ec683d96/20250804/i1754256020_4895_6.jpg","https://xcimg.szwego.com/img/ec683d96/20250804/i1754256019_1089_0.jpg","https://xcimg.szwego.com/img/ec683d96/20250804/i1754256020_1666_5.jpg","https://xcimg.szwego.com/img/ec683d96/20250804/i1754256019_5866_3.jpg"],"created_at":"2025-09-19T03:27:53.575Z"}
