{"id":"item-d0f7cd673d8e","sku":"_dx4x4YF6sFAHRk4syDSSQwshOv38dd57CLc2l5A","name_en":"顶级原单复刻独家实拍📷【Chess Messenger 四方袋】N40561 红色(格子)","name_cn":"顶级原单复刻独家实拍📷【Chess Messenger 四方袋】N40561 红色(格子)\n\n创意总监Pharrell Williams受到众议院标志性的Damier检查的启发,在他的新Damier Pop涂层帆布上创造了这个国际象棋信使包的独特形状。该包结合了其他房屋设计线索,包括天然皮革装饰、加固的角落和顶部手柄。可拆卸的表带可调整为斜挎携带。\n\n尺寸: 24 x 24 x 8厘米","specs":{"source":"wsxcme","sourceId":"_dx4x4YF6sFAHRk4syDSSQwshOv38dd57CLc2l5A","sourceTagId":47002622,"sourceTagName":"LV/女包","dimensions":{"lengthCm":24,"heightCm":24,"widthCm":8},"rawTitle":"顶级原单复刻独家实拍📷【Chess Messenger 四方袋】N40561 红色(格子)\n\n创意总监Pharrell Williams受到众议院标志性的Damier检查的启发,在他的新Damier Pop涂层帆布上创造了这个国际象棋信使包的独特形状。该包结合了其他房屋设计线索,包括天然皮革装饰、加固的角落和顶部手柄。可拆卸的表带可调整为斜挎携带。\n\n尺寸: 24 x 24 x 8厘米"},"price":null,"currency":"CNY","moq":1,"category":"lv-women-bags","status":"active","alibaba_url":null,"images":["https://xcimg.szwego.com/20240702/i1719907361_9199_0.jpg","https://xcimg.szwego.com/20240702/i1719907361_7707_1.jpg","https://xcimg.szwego.com/20240702/i1719907361_2130_2.jpg","https://xcimg.szwego.com/20240702/i1719907361_8067_3.jpg","https://xcimg.szwego.com/20240702/i1719907361_5009_4.jpg","https://xcimg.szwego.com/20240702/i1719907361_8469_5.jpg","https://xcimg.szwego.com/20240702/i1719907361_1638_6.jpg","https://xcimg.szwego.com/20240702/i1719907361_3503_7.jpg","https://xcimg.szwego.com/20240702/i1719907361_3799_8.jpg"],"created_at":"2025-02-08T11:28:59.515Z"}
