{"id":"item-8ba8cec3667b","sku":"_dUoUoMIVNiLXhJjtOeSj6TQWAGdL_Vg_ZPqtqlg","name_en":"FENDI ‣PEEKABOO","name_cn":"FENDI ‣PEEKABOO\n      采用七层油边涂抹工艺配合手工缝制蜡线 皮纹清晰有质感 越用越柔软的t0go 历经岁月之后更有味道。23-12-18\n款号244","specs":{"source":"wsxcme","sourceId":"_dUoUoMIVNiLXhJjtOeSj6TQWAGdL_Vg_ZPqtqlg","sourceTagId":47002731,"sourceTagName":"芬迪/女包","modelNumber":"244","rawTitle":"FENDI ‣PEEKABOO\n      采用七层油边涂抹工艺配合手工缝制蜡线 皮纹清晰有质感 越用越柔软的t0go 历经岁月之后更有味道。23-12-18\n款号244"},"price":null,"currency":"CNY","moq":1,"category":"fendi-women-bags","status":"active","alibaba_url":null,"images":["https://xcimg.szwego.com/20220317/i1647452412_7126_0.jpg","https://xcimg.szwego.com/20220317/i1647452412_1324_1.jpg","https://xcimg.szwego.com/20220317/i1647452412_3457_2.jpg","https://xcimg.szwego.com/20220317/i1647452412_4229_3.jpg","https://xcimg.szwego.com/20220317/i1647452412_6724_4.jpg","https://xcimg.szwego.com/20220317/i1647452412_5385_5.jpg","https://xcimg.szwego.com/20220317/i1647452412_5528_6.jpg","https://xcimg.szwego.com/20220317/i1647452412_8882_7.jpg","https://xcimg.szwego.com/20220317/i1647452412_1275_8.jpg"],"created_at":"2024-11-11T10:33:53.482Z"}
