{"id":"item-5122a9be799c","sku":"_dvRvRUnOJyn3EzAKth1qsFtHcoqDw77vga_NW5w","name_en":"Horizontal Bobby in stock!!️","name_cn":"Horizontal Bobby in stock!!️\nLatest Bobby series crossbody bag, a bag that looks hundreds of times better in person than in pictures 🙋🏻‍♀️, exquisite and stylish, excellent grain calf leather 🐂, both high-end and durable, adjustable strap, very spacious, easily fits two phones, and most importantly, goes perfectly with outfits 😘\nsize:21*5*12cm\n9327","specs":{"source":"wsxcme","sourceId":"_dvRvRUnOJyn3EzAKth1qsFtHcoqDw77vga_NW5w","sourceTagId":47002747,"sourceTagName":"Dior/women's bag","rawTitle":"Horizontal Bobby in stock!!️\nLatest Bobby series crossbody bag, a bag that looks hundreds of times better in person than in pictures 🙋🏻‍♀️, exquisite and stylish, excellent grain calf leather 🐂, both high-end and durable, adjustable strap, very spacious, easily fits two phones, and most importantly, goes perfectly with outfits 😘\nsize:21*5*12cm\n9327"},"price":null,"currency":"CNY","moq":1,"category":"dior-women-bags","status":"active","alibaba_url":null,"images":["https://xcimg.szwego.com/20230625/i1687705055_6731_0.jpg","https://xcimg.szwego.com/20230625/i1687705055_992_1.jpg","https://xcimg.szwego.com/20230625/i1687705055_7494_2.jpg","https://xcimg.szwego.com/20230625/i1687705055_5049_3.jpg","https://xcimg.szwego.com/20230625/i1687705055_6949_4.jpg","https://xcimg.szwego.com/20230625/i1687705055_1252_5.jpg","https://xcimg.szwego.com/20230625/i1687705055_3551_6.jpg","https://xcimg.szwego.com/20230625/i1687705055_5893_7.jpg","https://xcimg.szwego.com/20230625/i1687705055_6618_8.jpg"],"created_at":"2024-07-12T05:20:39.503Z"}
