{"id":"item-86649135df92","sku":"_dcUcU6xXfBV77KsPcfGwN09vesfdK9M7Oka_Hwg","name_en":"Goyard Women Bags","name_cn":"戈雅 镇店之宝销量王🔥再次回货❗️\ngoyard hobo拉链托特 \nw多买的zp回来开发\ngoyard对于托特包型的拿捏我一向很放心\n做到了优雅,法式,又可以日常休闲\n单肩带让整个包的线条干净利落\n不带一丝一毫的拖沓\n列入我的年度top了~\n手柄包边等配皮是头层真皮\n请务必区分市场超纤货❌\n 42×27×15cm\n款号:020223\n.","specs":{"source":"wsxcme","sourceId":"_dcUcU6xXfBV77KsPcfGwN09vesfdK9M7Oka_Hwg","sourceTagId":47003160,"sourceTagName":"戈雅/女包","modelNumber":"020223","rawTitle":"戈雅 镇店之宝销量王🔥再次回货❗️\ngoyard hobo拉链托特 \nw多买的zp回来开发\ngoyard对于托特包型的拿捏我一向很放心\n做到了优雅,法式,又可以日常休闲\n单肩带让整个包的线条干净利落\n不带一丝一毫的拖沓\n列入我的年度top了~\n手柄包边等配皮是头层真皮\n请务必区分市场超纤货❌\n 42×27×15cm\n款号:020223\n."},"price":null,"currency":"CNY","moq":1,"category":"goyard-women-bags","status":"active","alibaba_url":null,"images":["https://xcimg.szwego.com/20230905/i1693897405_4766_0.jpg","https://xcimg.szwego.com/20230905/i1693897405_1911_1.jpg","https://xcimg.szwego.com/20230905/i1693897405_614_2.jpg","https://xcimg.szwego.com/20230905/i1693897405_4280_3.jpg","https://xcimg.szwego.com/20230905/i1693897405_7001_8.jpg","https://xcimg.szwego.com/20230905/i1693897405_1781_4.jpg","https://xcimg.szwego.com/20230905/i1693897405_3879_5.jpg","https://xcimg.szwego.com/20230905/i1693897405_6589_6.jpg","https://xcimg.szwego.com/20230905/i1693897405_7636_7.jpg"],"created_at":"2025-03-28T13:52:34.506Z"}
