{"id":"item-7c20946d4c87","sku":"_dQ8Q8U8qGpsg6yWQiy3AEDG9qazT0YE15hkEZyg","name_en":"Dior Women Bags","name_cn":"顶级原单 配全套包装\n最新Dior夏季牛仔布系列蓝色小号尺寸出货了!!️\nDior D-Joybag丹宁牛仔有️这系列今年晋升为新的得力干将啊!火爆程度不亚于任何一只经典款,😊在之前的钻石元素加持下又推出牛仔系列,尤其同色系树logo吊坠,直接把火添到了巅峰,又掀起一阵牛仔狂潮,人间绝品仅此这只👍\n\nSize;22.5*12*5.5cm","specs":{"source":"wsxcme","sourceId":"_dQ8Q8U8qGpsg6yWQiy3AEDG9qazT0YE15hkEZyg","sourceTagId":47002747,"sourceTagName":"迪奥/女包","rawTitle":"顶级原单 配全套包装\n最新Dior夏季牛仔布系列蓝色小号尺寸出货了!!️\nDior D-Joybag丹宁牛仔有️这系列今年晋升为新的得力干将啊!火爆程度不亚于任何一只经典款,😊在之前的钻石元素加持下又推出牛仔系列,尤其同色系树logo吊坠,直接把火添到了巅峰,又掀起一阵牛仔狂潮,人间绝品仅此这只👍\n\nSize;22.5*12*5.5cm"},"price":null,"currency":"CNY","moq":1,"category":"dior-women-bags","status":"active","alibaba_url":null,"images":["https://xcimg.szwego.com/20230511/i1683786072_1550_0.jpg","https://xcimg.szwego.com/20230511/i1683786072_4566_1.jpg","https://xcimg.szwego.com/20230511/i1683786141_283_0.jpg","https://xcimg.szwego.com/20230511/i1683786072_9389_3.jpg","https://xcimg.szwego.com/20230511/i1683786072_7542_4.jpg","https://xcimg.szwego.com/20230511/i1683786072_9846_5.jpg","https://xcimg.szwego.com/20230511/i1683786072_6479_6.jpg","https://xcimg.szwego.com/20230511/i1683786072_258_7.jpg","https://xcimg.szwego.com/20230511/i1683786072_2472_8.jpg"],"created_at":"2024-11-11T10:24:39.702Z"}
